innertube/__init__.py
innertube/adaptor.py
innertube/api.py
innertube/clients.py
innertube/config.py
innertube/enums.py
innertube/errors.py
innertube/locale.py
innertube/models.py
innertube/protocols.py
innertube/py.typed
innertube/utils.py
innertube-2.1.18.dist-info/LICENSE
innertube-2.1.18.dist-info/METADATA
innertube-2.1.18.dist-info/WHEEL
innertube-2.1.18.dist-info/RECORD
