Metadata-Version: 2.1
Name: innertube
Version: 2.1.18
Summary: Python Client for Google's Private InnerTube API. Works with Youtube, YouTube Music and more!
Home-page: https://pypi.org/project/innertube/
License: MIT
Keywords: innertube,youtube,youtubei,python,api,client
Author: Tom Bulled
Author-email: 26026015+tombulled@users.noreply.github.com
Requires-Python: >=3.8,<4.0
Classifier: License :: OSI Approved :: MIT License
Classifier: Programming Language :: Python :: 3
Classifier: Programming Language :: Python :: 3.8
Classifier: Programming Language :: Python :: 3.9
Classifier: Programming Language :: Python :: 3.10
Classifier: Programming Language :: Python :: 3.11
Classifier: Programming Language :: Python :: 3.12
Requires-Dist: httpx (>=0.23.3,<0.24.0)
Requires-Dist: mediate (>=0.1.2,<0.2.0)
Project-URL: Repository, https://github.com/tombulled/innertube
